mumbleice/__init__.py
mumbleice/__main__.py
mumbleice/bot.py
mumbleice/icecast.py
mumbleice/mumble.py
mumbleice/utils.py
mumbleice/resources/streaming_started.wav
mumbleice/resources/streaming_stopped.wav
mumbleice-1.5.0.dist-info/LICENCE.md
mumbleice-1.5.0.dist-info/METADATA
mumbleice-1.5.0.dist-info/WHEEL
mumbleice-1.5.0.dist-info/entry_points.txt
mumbleice-1.5.0.dist-info/top_level.txt
mumbleice-1.5.0.dist-info/RECORD
