Metadata-Version: 2.1
Name: mumbleice
Version: 1.5.0
Summary: Mumble bot for streaming to Icecast
Home-page: https://github.com/bitcastza/mumbleice
Keywords: mumble audio icecast streaming
Classifier: Development Status :: 5 - Production/Stable
Classifier: Intended Audience :: Other Audience
Classifier: Topic :: Multimedia :: Sound/Audio
Classifier: Topic :: Communications
Classifier: License :: OSI Approved :: GNU General Public License v3 or later (GPLv3+)
Classifier: Environment :: Console
Classifier: Programming Language :: Python :: 3
Classifier: Programming Language :: Python :: 3.9
Classifier: Programming Language :: Python :: 3.10
Requires-Python: >=3.9
License-File: LICENCE.md
Requires-Dist: pymumble
Requires-Dist: ffmpeg-python
Requires-Dist: pydub
Requires-Dist: pyaml-env
